{"__symbolic":"module","version":4,"metadata":{"throwIfAlreadyLoaded":{"__symbolic":"function"},"We7Service":{"__symbolic":"class","decorators":[{"__symbolic":"call","expression":{"__symbolic":"reference","module":"@angular/core","name":"Injectable","line":2,"character":1}}],"members":{"__ctor__":[{"__symbolic":"constructor"}],"parseURL":[{"__symbolic":"method"}],"setQuerParams":[{"__symbolic":"method"}],"get":[{"__symbolic":"method"}],"getUrl":[{"__symbolic":"method"}],"getMobileUrl":[{"__symbolic":"method"}],"getWebUrl":[{"__symbolic":"method"}],"serializeQueryParams":[{"__symbolic":"method"}],"encodeUriQuery":[{"__symbolic":"method"}],"encodeUriString":[{"__symbolic":"method"}]}},"StartupService":{"__symbolic":"class","decorators":[{"__symbolic":"call","expression":{"__symbolic":"reference","module":"@angular/core","name":"Injectable","line":10,"character":1}}],"members":{"__ctor__":[{"__symbolic":"constructor","parameterDecorators":[null,null,null,null,[{"__symbolic":"call","expression":{"__symbolic":"reference","module":"@angular/core","name":"Inject","line":17,"character":9},"arguments":[{"__symbolic":"reference","module":"@delon/auth","name":"DA_SERVICE_TOKEN","line":17,"character":16}]}],null,null,null],"parameters":[{"__symbolic":"reference","module":"@delon/theme","name":"MenuService","line":13,"character":29},{"__symbolic":"reference","module":"@delon/theme","name":"SettingsService","line":14,"character":32},{"__symbolic":"reference","module":"@delon/acl","name":"ACLService","line":15,"character":28},{"__symbolic":"reference","module":"@delon/theme","name":"TitleService","line":16,"character":30},{"__symbolic":"reference","module":"@delon/auth","name":"ITokenService","line":17,"character":56},{"__symbolic":"reference","module":"@angular/common/http","name":"HttpClient","line":18,"character":28},{"__symbolic":"reference","module":"@angular/core","name":"Injector","line":19,"character":26},{"__symbolic":"reference","name":"We7Service"}]}],"load":[{"__symbolic":"method"}]}},"DefaultInterceptor":{"__symbolic":"class","decorators":[{"__symbolic":"call","expression":{"__symbolic":"reference","module":"@angular/core","name":"Injectable","line":16,"character":1}}],"members":{"__ctor__":[{"__symbolic":"constructor","parameters":[{"__symbolic":"reference","module":"@angular/core","name":"Injector","line":18,"character":34}]}],"goTo":[{"__symbolic":"method"}],"handleData":[{"__symbolic":"method"}],"intercept":[{"__symbolic":"method"}]}}},"origins":{"throwIfAlreadyLoaded":"./module-import-guard","We7Service":"./tools/we7.service","StartupService":"./startup/startup.service","DefaultInterceptor":"./net/default.interceptor"},"importAs":"we7-core"}